Metadata-Version: 1.0
Name: isOddNum
Version: 1.0.0
Summary: A function judging odd
Home-page: https://www.baidu.com
Author: qa.yw
Author-email: byteflow@163.com
License: UNKNOWN
Platform: UNKNOWN
